airflow_provider_sapiq/__about__.py
airflow_provider_sapiq/__init__.py
airflow_provider_sapiq/get_provider_info.py
airflow_provider_sapiq/py.typed
airflow_provider_sapiq/hooks/__init__.py
airflow_provider_sapiq/hooks/sapiq.py
airflow_provider_sapiq/operators/__init__.py
airflow_provider_sapiq/operators/sapiq.py
airflow_provider_sapiq-0.2.0.dist-info/METADATA
airflow_provider_sapiq-0.2.0.dist-info/WHEEL
airflow_provider_sapiq-0.2.0.dist-info/entry_points.txt
airflow_provider_sapiq-0.2.0.dist-info/licenses/LICENSE.txt
airflow_provider_sapiq-0.2.0.dist-info/RECORD
