Metadata-Version: 2.3
Name: airflow-provider-sapiq
Version: 0.2.0
Summary: SAP IQ provider for Apache Airflow
Project-URL: Documentation, https://github.com/ask1/airflow-provider-sapiq#readme
Project-URL: Issues, https://github.com/ask1/airflow-provider-sapiq/issues
Project-URL: Source, https://github.com/ask1/airflow-provider-sapiq
Author: Anatoli Skovpen
License-Expression: Apache-2.0
License-File: LICENSE.txt
Classifier: Development Status :: 4 - Beta
Classifier: Programming Language :: Python
Classifier: Programming Language :: Python :: 3.8
Classifier: Programming Language :: Python :: 3.9
Classifier: Programming Language :: Python :: 3.10
Classifier: Programming Language :: Python :: 3.11
Classifier: Programming Language :: Python :: 3.12
Classifier: Programming Language :: Python :: Implementation :: CPython
Classifier: Programming Language :: Python :: Implementation :: PyPy
Requires-Python: >=3.8
Requires-Dist: apache-airflow>=2.3.0
Requires-Dist: sqlalchemy-sqlany>=1.0.4
Requires-Dist: sqlanydb>=1.0.13
Provides-Extra: common-sql
Requires-Dist: apache-airflow-providers-common-sql; extra == 'common-sql'
